PythonX27
