Metadata-Version: 2.1
Name: PythonX27
Version: 0.0.1
Summary: PythonX27 is a powerful and intuitive module that extends the standard functions of Python by adding unique capabilities. With PythonX27, developers can perform complex tasks with greater precision and efficiency, alleviating concerns about the limitations of standard libraries. Designed with a focus on performance and ease of use, PythonX27 is an ideal choice for both professionals and newcomers.
Author: Creatorofpythonx
Author-email: organisator.bibliotek.py@gmail.com
License: Permissions: You are free to use, modify, distribute, and incorporate PythonX27 into your projects, both commercial and non-commercial, as long as you retain the copyright notice and this license in all copies or substantial portions of the library.
Classifier: License :: OSI Approved :: Apache Software License
Classifier: Operating System :: OS Independent
Classifier: Intended Audience :: End Users/Desktop
Classifier: Intended Audience :: Developers
Classifier: Programming Language :: Python
Classifier: Programming Language :: Python :: 3
Classifier: Programming Language :: Python :: 3.12
Classifier: Programming Language :: Python :: Implementation :: PyPy
Classifier: Programming Language :: Python :: Implementation :: CPython
